atomvision/__init__.py
atomvision/data/__init__.py
atomvision/data/graph.py
atomvision/data/stem.py
atomvision/data/stemconv.py
atomvision/models/__init__.py
atomvision/models/alignn_classifier.py
atomvision/models/cnn_classifiers.py
atomvision/models/gcn.py
atomvision/models/plotting.py
atomvision/models/segmentation_utils.py
atomvision/models/training_metrics.py
atomvision/models/training_utils.py
atomvision/scripts/__init__.py
atomvision/scripts/focal_loss.py
atomvision/scripts/generate_stem.py
atomvision/scripts/image_to_graph.py
atomvision/scripts/stem_conv.py
atomvision/scripts/train_autoencoder.py
atomvision/scripts/train_classifier_alignn.py
atomvision/scripts/train_classifier_cnn.py
atomvision/scripts/train_gan.py
atomvision/scripts/train_gnn_old.py
atomvision/scripts/train_segmentation.py
atomvision/scripts/train_tsne.py
atomvision/scripts/train_variational_autoencoder.py
atomvision-2023.5.6.data/scripts/stem_conv.py
atomvision-2023.5.6.data/scripts/train_autoencoder.py
atomvision-2023.5.6.data/scripts/train_classifier_alignn.py
atomvision-2023.5.6.data/scripts/train_classifier_cnn.py
atomvision-2023.5.6.data/scripts/train_gan.py
atomvision-2023.5.6.data/scripts/train_segmentation.py
atomvision-2023.5.6.data/scripts/train_tsne.py
atomvision-2023.5.6.dist-info/LICENSE.md
atomvision-2023.5.6.dist-info/METADATA
atomvision-2023.5.6.dist-info/WHEEL
atomvision-2023.5.6.dist-info/top_level.txt
atomvision-2023.5.6.dist-info/RECORD
