Metadata-Version: 2.1
Name: atomvision
Version: 2023.5.6
Summary: atomvision
Home-page: https://github.com/usnistgov/atomvision
Author: Kamal Choudhary, Brian DeCost
Author-email: kamal.choudhary@nist.gov
License: UNKNOWN
Platform: UNKNOWN
Classifier: Programming Language :: Python :: 3
Classifier: License :: OSI Approved :: MIT License
Classifier: Operating System :: OS Independent
Requires-Python: >=3.7
License-File: LICENSE.md
Requires-Dist: numpy (>=1.19.5)
Requires-Dist: scipy (>=1.6.3)
Requires-Dist: jarvis-tools (>=2021.07.19)
Requires-Dist: alignn (>=2022.10.23)
Requires-Dist: beautifulsoup4 (>=4.11.1)
Requires-Dist: scikit-image (>=0.19.3)
Requires-Dist: torch (>=1.12.0)
Requires-Dist: pyparsing (==2.2.1)
Requires-Dist: opencv-python (>=4.6.0.66)
Requires-Dist: typer
Requires-Dist: python-dotenv
Requires-Dist: segmentation-models-pytorch (>=0.2.1)
Requires-Dist: Pillow (>=9.2.0)
Requires-Dist: torchvision (>=0.13.0)
Requires-Dist: scikit-learn (>=0.24.1)
Requires-Dist: matplotlib (>=3.4.1)
Requires-Dist: seaborn (>=0.11.2)
Requires-Dist: tqdm (>=4.60.0)
Requires-Dist: pandas (>=1.2.4)
Requires-Dist: pytorch-ignite (>=0.5.0.dev20221024)
Requires-Dist: pydantic (==1.8.1)
Requires-Dist: flake8 (>=3.9.1)
Requires-Dist: pycodestyle (>=2.7.0)
Requires-Dist: pydocstyle (>=6.0.0)
